ez/__init__.py
ez/ez.py
ez/ezs.py
ez/eztk.py
seakyez-1.0.8.dist-info/LICENSE
seakyez-1.0.8.dist-info/METADATA
seakyez-1.0.8.dist-info/WHEEL
seakyez-1.0.8.dist-info/top_level.txt
seakyez-1.0.8.dist-info/RECORD
