Metadata-Version: 2.1
Name: seakyez
Version: 1.0.8
Summary: An package that makes Python programming easy.
Home-page: https://github.com/SeakyLuo/PythonFiles
Author: Seaky Lone
Author-email: luokiss9@qq.com
License: UNKNOWN
Platform: UNKNOWN
Classifier: Programming Language :: Python :: 3.7
Classifier: License :: OSI Approved :: MIT License
Classifier: Operating System :: OS Independent
